[
  {
    "ContainingType": "ASP.NET.Controllers.PostController",
    "Method": "Post",
    "RelativePath": "api/Post",
    "HttpMethod": "POST",
    "IsController": true,
    "Order": 0,
    "Parameters": [
      {
        "Name": "model",
        "Type": "ASP.NET.ModelsDTO.Post.CreatePostDto",
        "IsRequired": true
      }
    ],
    "ReturnTypes": []
  },
  {
    "ContainingType": "ASP.NET.Controllers.PostController",
    "Method": "Get",
    "RelativePath": "api/Post",
    "HttpMethod": "GET",
    "IsController": true,
    "Order": 0,
    "Parameters": [],
    "ReturnTypes": []
  },
  {
    "ContainingType": "ASP.NET.Controllers.UserController",
    "Method": "GetProfile",
    "RelativePath": "api/User/getProfile",
    "HttpMethod": "PUT",
    "IsController": true,
    "Order": 0,
    "Parameters": [],
    "ReturnTypes": []
  },
  {
    "ContainingType": "ASP.NET.Controllers.UserController",
    "Method": "Login",
    "RelativePath": "api/User/login",
    "HttpMethod": "POST",
    "IsController": true,
    "Order": 0,
    "Parameters": [
      {
        "Name": "model",
        "Type": "ASP.NET.Models.LoginCredentials",
        "IsRequired": true
      }
    ],
    "ReturnTypes": []
  },
  {
    "ContainingType": "ASP.NET.Controllers.UserController",
    "Method": "Logout",
    "RelativePath": "api/User/logout",
    "HttpMethod": "POST",
    "IsController": true,
    "Order": 0,
    "Parameters": [],
    "ReturnTypes": []
  },
  {
    "ContainingType": "ASP.NET.Controllers.UserController",
    "Method": "Register",
    "RelativePath": "api/User/register",
    "HttpMethod": "POST",
    "IsController": true,
    "Order": 0,
    "Parameters": [
      {
        "Name": "model",
        "Type": "ASP.NET.ModelsDTO.User.UserRegisterModel",
        "IsRequired": true
      }
    ],
    "ReturnTypes": []
  },
  {
    "ContainingType": "ASP.NET.Controllers.WeatherForecastController",
    "Method": "Get",
    "RelativePath": "WeatherForecast",
    "HttpMethod": "GET",
    "IsController": true,
    "Order": 0,
    "Parameters": [],
    "ReturnTypes": [
      {
        "Type": "System.Collections.Generic.IEnumerable\u00601[[ASP.NET.WeatherForecast, ASP.NET, Version=1.0.0.0, Culture=neutral, PublicKeyToken=null]]",
        "MediaTypes": [
          "text/plain",
          "application/json",
          "text/json"
        ],
        "StatusCode": 200
      }
    ],
    "EndpointName": "GetWeatherForecast"
  }
]